{
  "$schema": "https://developer.microsoft.com/json-schemas/fabric/item/report/definition/visualContainer/1.5.0/schema.json",
  "name": "261e44a37518389cd354",
  "position": {
    "x": 1127.1337579617834,
    "y": 50.276008492569,
    "z": 0,
    "height": 65.902335456475583,
    "width": 141.31634819532908,
    "tabOrder": 0
  },
  "visual": {
    "visualType": "slicer",
    "query": {
      "queryState": {
        "Values": {
          "projections": [
            {
              "field": {
                "Column": {
                  "Expression": {
                    "SourceRef": {
                      "Entity": "Rolling Months"
                    }
                  },
                  "Property": "Rolling Months"
                }
              },
              "queryRef": "Rolling Months.Rolling Months",
              "nativeQueryRef": "Rolling Months",
              "active": true
            }
          ]
        }
      }
    },
    "objects": {
      "data": [
        {
          "properties": {
            "numericStart": {
              "expr": {
                "Literal": {
                  "Value": "12D"
                }
              }
            }
          }
        }
      ],
      "general": [
        {
          "properties": {
            "filter": {
              "filter": {
                "Version": 2,
                "From": [
                  {
                    "Name": "r",
                    "Entity": "Rolling Months",
                    "Type": 0
                  }
                ],
                "Where": [
                  {
                    "Condition": {
                      "Comparison": {
                        "ComparisonKind": 0,
                        "Left": {
                          "Column": {
                            "Expression": {
                              "SourceRef": {
                                "Source": "r"
                              }
                            },
                            "Property": "Rolling Months"
                          }
                        },
                        "Right": {
                          "Literal": {
                            "Value": "12D"
                          }
                        }
                      }
                    }
                  }
                ]
              }
            },
            "responsive": {
              "expr": {
                "Literal": {
                  "Value": "false"
                }
              }
            }
          }
        }
      ],
      "slider": [
        {
          "properties": {
            "show": {
              "expr": {
                "Literal": {
                  "Value": "false"
                }
              }
            }
          }
        }
      ],
      "header": [
        {
          "properties": {
            "textSize": {
              "expr": {
                "Literal": {
                  "Value": "9D"
                }
              }
            }
          }
        }
      ]
    },
    "visualContainerObjects": {
      "visualHeader": [
        {
          "properties": {
            "show": {
              "expr": {
                "Literal": {
                  "Value": "false"
                }
              }
            }
          }
        }
      ],
      "general": [
        {
          "properties": {
            "keepLayerOrder": {
              "expr": {
                "Literal": {
                  "Value": "true"
                }
              }
            }
          }
        }
      ]
    },
    "drillFilterOtherVisuals": true
  }
}